dc43_service_clients/__init__.py
dc43_service_clients/_http_sync.py
dc43_service_clients/_pytest_runner.py
dc43_service_clients/bootstrap.py
dc43_service_clients/odps.py
dc43_service_clients/contracts/__init__.py
dc43_service_clients/contracts/client/__init__.py
dc43_service_clients/contracts/client/interface.py
dc43_service_clients/contracts/client/local.py
dc43_service_clients/contracts/client/remote.py
dc43_service_clients/data_products/__init__.py
dc43_service_clients/data_products/_compat.py
dc43_service_clients/data_products/_types.py
dc43_service_clients/data_products/models.py
dc43_service_clients/data_products/client/__init__.py
dc43_service_clients/data_products/client/interface.py
dc43_service_clients/data_products/client/local.py
dc43_service_clients/data_products/client/remote.py
dc43_service_clients/data_quality/__init__.py
dc43_service_clients/data_quality/models.py
dc43_service_clients/data_quality/transport.py
dc43_service_clients/data_quality/client/__init__.py
dc43_service_clients/data_quality/client/interface.py
dc43_service_clients/data_quality/client/local.py
dc43_service_clients/data_quality/client/remote.py
dc43_service_clients/governance/__init__.py
dc43_service_clients/governance/lineage.py
dc43_service_clients/governance/models.py
dc43_service_clients/governance/publication.py
dc43_service_clients/governance/transport.py
dc43_service_clients/governance/client/__init__.py
dc43_service_clients/governance/client/interface.py
dc43_service_clients/governance/client/local.py
dc43_service_clients/governance/client/remote.py
dc43_service_clients/testing/__init__.py
dc43_service_clients/testing/backends.py
dc43_service_clients-0.32.0.0.dist-info/METADATA
dc43_service_clients-0.32.0.0.dist-info/WHEEL
dc43_service_clients-0.32.0.0.dist-info/entry_points.txt
dc43_service_clients-0.32.0.0.dist-info/top_level.txt
dc43_service_clients-0.32.0.0.dist-info/RECORD
